setup.cfg
setup.py
ordinaldate/__init__.py
ordinaldate/ordinaldate.py
ordinaldate.egg-info/PKG-INFO
ordinaldate.egg-info/SOURCES.txt
ordinaldate.egg-info/dependency_links.txt
ordinaldate.egg-info/top_level.txt
tests/__init__.py
tests/test_ordinaldate.py