Metadata-Version: 1.1
Name: ordinaldate
Version: 1.0.0
Summary: Python module to create dates based on the (first, second, third, etc) day of the week in a month
Home-page: http://github.com/brianjbuck/ordinaldate/
Author: Brian Buck
Author-email: brian@thebuckpasser.com
License: MIT Software License
Download-URL: https://github.com/brianjbuck/ordinaldate/tarball/1.0.0/
Platform: any
Classifier: Programming Language :: Python
Classifier: Programming Language :: Python :: 3.4
Classifier: Programming Language :: Python :: 3.5
Classifier: Development Status :: 4 - Beta
Classifier: Natural Language :: English
Classifier: Intended Audience :: Developers
Classifier: License :: OSI Approved :: MIT License
Classifier: Operating System :: OS Independent
Classifier: Topic :: Software Development :: Libraries :: Python Modules
